{
  "products": [
    {
      "id": "2",
      "name": "Product 2",
      "price": 200,
      "description": "This is product 2",
      "category": "Category 2",
      "stock": 19
    },
    {
      "id": "3",
      "name": "Product 3",
      "price": 300,
      "description": "This is product 3",
      "category": "Category 3",
      "stock": 29
    },
    {
      "id": "4",
      "name": "Product 4",
      "price": 400,
      "description": "This is product 4",
      "category": "Category 4",
      "stock": 39
    },
    {
      "id": "5",
      "name": "Product 5",
      "price": 500,
      "description": "This is product 5",
      "category": "Category 5",
      "stock": 50
    },
    {
      "id": "2a56",
      "name": "Laptop",
      "price": 1000,
      "description": "A high-performance laptop",
      "category": "electronics",
      "stock": 10
    }
  ],
  "users": [
    {
      "id": "1",
      "name": "User 1",
      "email": "temo@gmail.com",
      "cart": [],
      "purchaseHistory": [
        {
          "id": "1",
          "name": "Product 1",
          "price": 100,
          "description": "This is product 1",
          "category": "Category 1",
          "stock": 10
        },
        {
          "id": "2",
          "name": "Product 2",
          "price": 200,
          "description": "This is product 2",
          "category": "Category 2",
          "stock": 19
        },
        {
          "id": "3",
          "name": "Product 3",
          "price": 300,
          "description": "This is product 3",
          "category": "Category 3",
          "stock": 29
        },
        {
          "id": "4",
          "name": "Product 4",
          "price": 400,
          "description": "This is product 4",
          "category": "Category 4",
          "stock": 39
        }
      ]
    },
    {
      "id": "2",
      "name": "User 2",
      "email": "user@gmail.com",
      "cart": [],
      "purchaseHistory": []
    }
  ]
}